Metadata-Version: 2.1
Name: jiexi_docx_server
Version: 1.0.1
Summary: 解析菁优网docx试卷
Home-page: UNKNOWN
Author: sirun.wang
Author-email: 870355373@qq.com
License: UNKNOWN
Keywords: 17content_render
Platform: UNKNOWN
